aws/__init__.py
aws/cert.py
aws/cfm.py
aws/cluster.py
aws/config.py
aws/ec2.py
aws/elb.py
aws/factsheet.py
aws/iam.py
aws/lambda_fn.py
aws/rds.py
aws/region.py
aws/secret.py
aws/util.py
aws/lambdas/rds/package.zip
aws/lambdas/startstop/eks-start/package.zip
aws/lambdas/startstop/eks-stop/package.zip
aws/templates/cfm/00-cert.yml
aws/templates/cfm/01-vpc.yml
aws/templates/cfm/02-eks-cp.yml
aws/templates/cfm/03-eks-workers.yml
aws/templates/cfm/04-rds.yml
aws/templates/cfm/ecr.yml
aws/templates/cfm/eks-startstop.yml
aws/templates/cfm/lambda.yml
aws/templates/cfm/s3-gov-hosting.yml
aws/templates/cfm/s3-hosting.yml
aws/templates/cfm/s3-storage.yml
aws/templates/cfm/vpc-endpoint.yml
aws/templates/factsheet/app-factsheet.md
aws/templates/factsheet/cluster-factsheet.md
atomic_cloud-2.0.1.dist-info/METADATA
atomic_cloud-2.0.1.dist-info/WHEEL
atomic_cloud-2.0.1.dist-info/top_level.txt
atomic_cloud-2.0.1.dist-info/RECORD
