Metadata-Version: 2.1
Name: atomic-cloud
Version: 2.0.1
Summary: Helper library to automate cloud environment management.
Home-page: https://gitlab.com/python-cicd/atomic-cloud
Author: SimonComputing, Inc.
Author-email: simon@simoncomputing.com
License: MIT
Platform: UNKNOWN
Classifier: License :: OSI Approved :: MIT License
Classifier: Programming Language :: Python :: 3
Classifier: Programming Language :: Python :: 3.7
Requires-Dist: boto3
Requires-Dist: botocore
Requires-Dist: Jinja2
Requires-Dist: cryptography
Requires-Dist: requests
Requires-Dist: pyyaml
